nestipy_inertia/__init__.py
nestipy_inertia/builder.py
nestipy_inertia/config.py
nestipy_inertia/exceptions.py
nestipy_inertia/inertia.py
nestipy_inertia/middleware.py
nestipy_inertia/module.py
nestipy_inertia/response.py
nestipy_inertia/service.py
nestipy_inertia/templating.py
nestipy_inertia/utils.py
nestipy_inertia-0.1.6.dist-info/LICENSE
nestipy_inertia-0.1.6.dist-info/METADATA
nestipy_inertia-0.1.6.dist-info/WHEEL
nestipy_inertia-0.1.6.dist-info/RECORD
