Metadata-Version: 2.1
Name: nestipy-inertia
Version: 0.1.6
Summary: Inertia package adapter for Nestipy
Author: Tsiresy Milà
Author-email: tsiresymila@gmail.com
Requires-Python: >=3.11,<4.0
Classifier: Programming Language :: Python :: 3
Classifier: Programming Language :: Python :: 3.11
Classifier: Programming Language :: Python :: 3.12
Classifier: Programming Language :: Python :: 3.13
